{"trial_id": "03", "hyperparameters": {"space": [{"class_name": "Float", "config": {"name": "learning_rate", "default": 0.0001, "conditions": [], "min_value": 0.0001, "max_value": 0.1, "step": null, "sampling": "log"}}, {"class_name": "Choice", "config": {"name": "loss", "default": "mean_absolute_error", "conditions": [], "values": ["mean_absolute_error", "mean_squared_error"], "ordered": false}}], "values": {"learning_rate": 0.00018714543011747007, "loss": "mean_squared_error"}}, "metrics": {"metrics": {"loss": {"direction": "min", "observations": [{"value": [0.43117469549179077], "step": 99}]}, "val_loss": {"direction": "min", "observations": [{"value": [0.37779685854911804], "step": 99}]}}}, "score": 0.37779685854911804, "best_step": 99, "status": "COMPLETED", "message": null}